Workbook

Sheet Summary
A1: Ledgerly — remaining steps
A2: As of October 7, 2026. Change the Status column on the Steps sheet and these counts update.
A4: Phase | B4: Total | C4: Done | D4: Left | E4: % done
A5: 1 · Now | B5: =COUNTIF(Steps!$B:$B,A5) | C5: =COUNTIFS(Steps!$B:$B,A5,Steps!$H:$H,"Done") | D5: =B5-C5 | E5: =IF(B5=0,0,C5/B5)
A6: 2 · Before launch | B6: =COUNTIF(Steps!$B:$B,A6) | C6: =COUNTIFS(Steps!$B:$B,A6,Steps!$H:$H,"Done") | D6: =B6-C6 | E6: =IF(B6=0,0,C6/B6)
A7: 3 · Launch day | B7: =COUNTIF(Steps!$B:$B,A7) | C7: =COUNTIFS(Steps!$B:$B,A7,Steps!$H:$H,"Done") | D7: =B7-C7 | E7: =IF(B7=0,0,C7/B7)
A8: 4 · After launch | B8: =COUNTIF(Steps!$B:$B,A8) | C8: =COUNTIFS(Steps!$B:$B,A8,Steps!$H:$H,"Done") | D8: =B8-C8 | E8: =IF(B8=0,0,C8/B8)
A9: 5 · Later | B9: =COUNTIF(Steps!$B:$B,A9) | C9: =COUNTIFS(Steps!$B:$B,A9,Steps!$H:$H,"Done") | D9: =B9-C9 | E9: =IF(B9=0,0,C9/B9)
A10: All | B10: =SUM(B5:B9) | C10: =SUM(C5:C9) | D10: =SUM(D5:D9) | E10: =IF(B10=0,0,C10/B10)
A12: Who | B12: Left
A13: You | B13: =COUNTIF(Steps!$E:$E,A13)-COUNTIFS(Steps!$E:$E,A13,Steps!$H:$H,"Done")
A14: Me | B14: =COUNTIF(Steps!$E:$E,A14)-COUNTIFS(Steps!$E:$E,A14,Steps!$H:$H,"Done")
A15: Both | B15: =COUNTIF(Steps!$E:$E,A15)-COUNTIFS(Steps!$E:$E,A15,Steps!$H:$H,"Done")
A17: How to use this
A18: • “Me” means Claude: just ask in chat and I’ll do it.
A19: • Work top to bottom: phase 1 can all happen now, in any order.
A20: • Phase 2 waits on accounts (Apple, Google, Stripe activation).
A21: • Phase 3 starts when you tell me “go live”.
A22: • The Marketing sheet runs alongside phases 1–3.

Sheet Steps
A1: # | B1: Phase | C1: Area | D1: Step | E1: Who | F1: Where / how | G1: Why it matters | H1: Status | I1: Notes
A2: 1 | B2: 1 · Now | C2: Payments | D2: Activate your Stripe account (business details and bank account) | E2: You | F2: Stripe dashboard → Activate payments | G2: Needed before anyone can actually pay | H2: Not started
A3: 2 | B3: 1 · Now | C3: Payments | D3: Turn on customer emails: receipts, failed payments and upcoming renewals | E3: You | F3: Stripe → Settings → Customer emails | G3: Customers expect receipts and warnings before a renewal | H3: Not started
A4: 3 | B4: 1 · Now | C4: Payments | D4: Talk to an accountant about sales tax and decide on Stripe Tax | E4: You | F4: Accountant, then Stripe → Tax | G4: Some states tax software subscriptions | H4: Not started
A5: 4 | B5: 1 · Now | C5: Legal | D5: Choose the business name and state for the Terms (section 14) | E5: You | F5: Tell me and I’ll update the Terms | G5: The Terms need a legal owner and governing state | H5: Not started
A6: 5 | B6: 1 · Now | C6: Legal | D6: Have a lawyer read the Privacy Policy and Terms | E6: You | F6: app.myledgerlyapp.com/privacy.html and /terms.html | G6: Cheap insurance before taking money | H6: Not started
A7: 6 | B7: 1 · Now | C7: Support | D7: Send a test email to support@ and tell me which provider receives it | E7: You | F7: Your email app | G7: Makes sure help requests reach you | H7: Not started
A8: 7 | B8: 1 · Now | C8: Security | D8: Turn on 2-step sign-in for GitHub, Supabase, Stripe, Netlify, Resend, PostHog, Cloudflare, your domain registrar and your email | E8: You | F8: Each service’s security settings | G8: One stolen password could take the whole app down | H8: Not started
A9: 8 | B9: 1 · Now | C9: Security | D9: Turn on the domain transfer lock | E9: You | F9: Your domain registrar | G9: Stops someone moving your domain away | H9: Not started
A10: 9 | B10: 1 · Now | C10: Security | D10: Turn on Dependabot alerts and secret scanning | E10: You | F10: GitHub → Ledgerly → Settings → Code security | G10: Warns about risky packages and leaked keys | H10: Not started
A11: 10 | B11: 1 · Now | C11: Security | D11: Create Cloudflare Turnstile keys; put the site key in Netlify (VITE_TURNSTILE_SITE_KEY) and the secret in GitHub (TURNSTILE_SECRET_KEY) | E11: You | F11: Cloudflare → Turnstile | G11: Blocks bots from creating accounts | H11: Not started
A12: 11 | B12: 1 · Now | C12: Database | D12: Upgrade Supabase to Pro (daily backups) and keep the Spend Cap on | E12: You | F12: Supabase → Billing | G12: Free projects pause and have no daily backups | H12: Not started
A13: 12 | B13: 1 · Now | C13: Database | D13: Enforce SSL and turn on leaked-password protection | E13: You | F13: Supabase → Database settings and Auth → Passwords | G13: Basic account and data protection | H13: Not started
... A44: 43 | B44: 5 · Later | C44: Ideas | D44: Smaller month picker on Transactions and Insights | E44: Me | F44: docs/IDEAS.md | G44: Less space taken at the top | H44: Not started

Sheet Marketing
A1: Area | B1: Step | C1: Who | D1: Why | E1: Status
A2: Foundation | B2: Write a one-sentence promise for Ledgerly (who it’s for and what it does better) | C2: You | D2: Everything else builds on this | E2: Not started
A3: Foundation | B3: Pick 1–2 audiences to start with (for example couples, freelancers and small business owners using shared categories) | C3: You | D3: Shared categories are a real standout for business owners | E3: Not started
A4: Website | B4: Add real screenshots and a short demo video to the home page | C4: Both | D4: People decide in seconds | E4: Not started
A5: Website | B5: Add an email sign-up for launch news | C5: Me | D5: Build a list before the app stores open | E5: Not started
A6: Beta | B6: Give beta testers free Premium with promo QR codes and ask for honest feedback | C6: You | D6: Feedback plus your first testimonials | E6: Not started
A7: Beta | B7: Collect 3–5 quotes from testers (with permission) for the website and store listing | C7: You | D7: Social proof | E7: Not started
A8: Content | B8: Write short posts from the help guides (for example “How to pay yourself from a business budget”) | C8: Both | D8: Free search traffic over time | E8: Not started
A9: Social | B9: Pick one channel you enjoy (TikTok, Instagram, Reddit, YouTube) and post weekly | C9: You | D9: Consistency beats being everywhere | E9: Not started
A10: Launch | B10: Plan a launch week: email list, social posts, Product Hunt and relevant communities | C10: You | D10: One focused push gets early users | E10: Not started
A11: Store | B11: App Store keywords, subtitle and screenshots that show the Home page and goals | C11: Both | D11: Most app installs come from store search | E11: Not started
A12: Measure | B12: Watch sign-ups, first budget created and Premium upgrades in PostHog each week | C12: You | D12: Shows what’s working (no amounts or names are tracked) | E12: Not started
